rtl/gpu/gpu_vec.v
// =============================================================================
//  gpu_vec.v
//  GPU 스타일 벡터 연산기 (병렬 처리 / SIMD)
//
//  P개의 PE(Processing Element = 곱셈기)를 병렬로 배치하여
//  한 클록에 원소 P개씩 동시에 처리한다.
//  N개의 원소를 계산하려면 ceil(N/P) 클록이 필요하다.  ->  O(N/P) cycles
//
//  연산:  C[i] = A[i] * B[i]   (CPU 버전과 결과 동일)
// =============================================================================
`timescale 1ns / 1ps

module gpu_vec #(
    parameter integer N  = 16,   // 벡터 길이 (원소 개수)
    parameter integer DW = 8,    // 원소 비트 폭
    parameter integer P  = 4     // 병렬 PE 개수 (lane 수)
)(
    input  wire                  clk,
    input  wire                  rst,
    input  wire                  start,
    input  wire [N*DW-1:0]       a_flat,
    input  wire [N*DW-1:0]       b_flat,
    output reg  [N*2*DW-1:0]     c_flat,
    output reg                   busy,
    output reg                   done
);

    // 처리해야 할 그룹(=클록) 수 = ceil(N / P)
    localparam integer NGROUP = (N + P - 1) / P;
    localparam integer GIDXW  = (NGROUP <= 1) ? 1 : $clog2(NGROUP);

    reg [GIDXW:0] grp;   // 현재 처리 중인 그룹 인덱스 (0..NGROUP)

    // ----- P개의 PE를 병렬로 인스턴스화 -----
    // base = grp*P 부터 P개의 원소를 동시에 계산
    wire [2*DW-1:0] prod [0:P-1];
    genvar k;
    generate
        for (k = 0; k < P; k = k + 1) begin : LANE
            // 이번 그룹에서 이 lane 이 담당하는 전역 인덱스
            wire [31:0]     gi   = grp * P + k;
            // 범위를 벗어나는 lane 은 0 으로 (N 이 P 의 배수가 아닐 때)
            wire [DW-1:0]   a_in = (gi < N) ? a_flat[gi*DW +: DW] : {DW{1'b0}};
            wire [DW-1:0]   b_in = (gi < N) ? b_flat[gi*DW +: DW] : {DW{1'b0}};
            assign prod[k] = a_in * b_in;   // 병렬 곱셈기
        end
    endgenerate

    integer j;
    always @(posedge clk) begin
        if (rst) begin
            grp    <= 0;
            busy   <= 1'b0;
            done   <= 1'b0;
            c_flat <= {N*2*DW{1'b0}};
        end else begin
            done <= 1'b0;

            if (start && !busy) begin
                grp  <= 0;
                busy <= 1'b1;
            end else if (busy) begin
                // 한 클록에 P개 원소 동시 기록 (병렬)
                for (j = 0; j < P; j = j + 1) begin
                    if (grp*P + j < N)
                        c_flat[(grp*P + j)*2*DW +: 2*DW] <= prod[j];
                end

                if (grp == NGROUP-1) begin
                    busy <= 1'b0;
                    done <= 1'b1;
                    grp  <= 0;
                end else begin
                    grp <= grp + 1'b1;
                end
            end
        end
    end

endmodule

rtl/cpu/cpu_vec.v
// =============================================================================
//  cpu_vec.v
//  CPU 스타일 벡터 연산기 (순차 처리 / Sequential)
//
//  단 하나의 MAC(곱셈기) 자원을 사용하여 한 클록에 원소 1개씩 처리한다.
//  N개의 원소를 계산하려면 N 클록이 필요하다.  ->  O(N) cycles
//
//  연산:  C[i] = A[i] * B[i]   (i = 0 .. N-1)
// =============================================================================
`timescale 1ns / 1ps

module cpu_vec #(
    parameter integer N  = 16,   // 벡터 길이 (원소 개수)
    parameter integer DW = 8     // 원소 비트 폭
)(
    input  wire                  clk,
    input  wire                  rst,      // 동기 리셋 (active-high)
    input  wire                  start,    // 1클록 펄스: 연산 시작
    input  wire [N*DW-1:0]       a_flat,   // 입력 벡터 A (flatten)
    input  wire [N*DW-1:0]       b_flat,   // 입력 벡터 B (flatten)
    output reg  [N*2*DW-1:0]     c_flat,   // 출력 벡터 C (flatten, 2*DW 폭)
    output reg                   busy,     // 연산 진행 중
    output reg                   done      // 1클록 펄스: 연산 완료
);

    // ----- 내부 상태 -----
    localparam integer IDXW = (N <= 1) ? 1 : $clog2(N);

    reg [IDXW:0] idx;   // 현재 처리 중인 원소 인덱스 (0..N)

    // 현재 인덱스의 원소 슬라이스
    wire [DW-1:0]   a_elem = a_flat[idx*DW +: DW];
    wire [DW-1:0]   b_elem = b_flat[idx*DW +: DW];
    wire [2*DW-1:0] prod   = a_elem * b_elem;   // 단일 곱셈기

    always @(posedge clk) begin
        if (rst) begin
            idx    <= 0;
            busy   <= 1'b0;
            done   <= 1'b0;
            c_flat <= {N*2*DW{1'b0}};
        end else begin
            done <= 1'b0;                 // 기본값 (펄스)

            if (start && !busy) begin
                // 연산 시작
                idx  <= 0;
                busy <= 1'b1;
            end else if (busy) begin
                // 한 클록에 원소 1개 처리 (순차)
                c_flat[idx*2*DW +: 2*DW] <= prod;

                if (idx == N-1) begin
                    busy <= 1'b0;
                    done <= 1'b1;         // 마지막 원소 계산 완료
                    idx  <= 0;
                end else begin
                    idx <= idx + 1'b1;
                end
            end
        end
    end

endmodule

tb/tb_compare.v
// =============================================================================
//  tb_compare.v
//  CPU(순차) vs GPU(병렬) 벡터 연산기 비교 테스트벤치
//
//  1) 동일한 입력 벡터 A, B 를 두 설계에 인가
//  2) 각 설계의 동작 사이클 수(=연산 시간)를 측정
//  3) 두 설계의 결과가 서로 같은지, 그리고 소프트웨어 golden 값과
//     일치하는지 검증
//  4) 속도(사이클/시간) 비교 및 speedup 출력
// =============================================================================
`timescale 1ns / 1ps

module tb_compare #(
    // ----- 파라미터 (커맨드라인 -P 로 override 가능) -----
    parameter integer N      = 16,    // 벡터 길이
    parameter integer DW     = 8,     // 원소 비트 폭
    parameter integer P      = 4,     // GPU 병렬 PE 수
    parameter integer CLK_NS = 10     // 클록 주기 10ns (100MHz)
);

    // ----- 공통 신호 -----
    reg                  clk;
    reg                  rst;
    reg  [N*DW-1:0]      a_flat;
    reg  [N*DW-1:0]      b_flat;

    // CPU 측 신호
    reg                  cpu_start;
    wire [N*2*DW-1:0]    cpu_c;
    wire                 cpu_busy, cpu_done;

    // GPU 측 신호
    reg                  gpu_start;
    wire [N*2*DW-1:0]    gpu_c;
    wire                 gpu_busy, gpu_done;

    // 측정/검증용
    integer cpu_cycles, gpu_cycles;
    integer i, errors;
    reg [2*DW-1:0] golden [0:N-1];

    // ----- DUT 인스턴스 -----
    cpu_vec #(.N(N), .DW(DW)) u_cpu (
        .clk(clk), .rst(rst), .start(cpu_start),
        .a_flat(a_flat), .b_flat(b_flat),
        .c_flat(cpu_c), .busy(cpu_busy), .done(cpu_done)
    );

    gpu_vec #(.N(N), .DW(DW), .P(P)) u_gpu (
        .clk(clk), .rst(rst), .start(gpu_start),
        .a_flat(a_flat), .b_flat(b_flat),
        .c_flat(gpu_c), .busy(gpu_busy), .done(gpu_done)
    );

    // ----- 클록 생성 -----
    always #(CLK_NS/2) clk = ~clk;

    // ----- 입력 벡터 준비 + 소프트웨어 golden 계산 -----
    task setup_vectors;
        integer k;
        reg [DW-1:0] av, bv;
        begin
            a_flat = 0;
            b_flat = 0;
            for (k = 0; k < N; k = k + 1) begin
                av = $random;            // 8비트 랜덤
                bv = $random;
                a_flat[k*DW +: DW] = av;
                b_flat[k*DW +: DW] = bv;
                golden[k] = av * bv;     // 기대값
            end
        end
    endtask

    // ----- CPU 실행 + 사이클 측정 -----
    task run_cpu;
        begin
            @(negedge clk);
            cpu_start = 1'b1;
            @(negedge clk);
            cpu_start = 1'b0;
            cpu_cycles = 0;
            // busy 가 풀리고 done 이 뜰 때까지 클록 카운트
            while (!cpu_done) begin
                @(posedge clk);
                cpu_cycles = cpu_cycles + 1;
            end
        end
    endtask

    // ----- GPU 실행 + 사이클 측정 -----
    task run_gpu;
        begin
            @(negedge clk);
            gpu_start = 1'b1;
            @(negedge clk);
            gpu_start = 1'b0;
            gpu_cycles = 0;
            while (!gpu_done) begin
                @(posedge clk);
                gpu_cycles = gpu_cycles + 1;
            end
        end
    endtask

    // ----- 결과 검증 -----
    task check_results;
        reg [2*DW-1:0] cval, gval;
        begin
            errors = 0;
            for (i = 0; i < N; i = i + 1) begin
                cval = cpu_c[i*2*DW +: 2*DW];
                gval = gpu_c[i*2*DW +: 2*DW];
                if (cval !== golden[i]) begin
                    $display("  [FAIL] CPU C[%0d] = %0d, expected %0d", i, cval, golden[i]);
                    errors = errors + 1;
                end
                if (gval !== golden[i]) begin
                    $display("  [FAIL] GPU C[%0d] = %0d, expected %0d", i, gval, golden[i]);
                    errors = errors + 1;
                end
            end
        end
    endtask

    // ----- 메인 시퀀스 -----
    initial begin
        $dumpfile("sim/wave.vcd");
        $dumpvars(0, tb_compare);

        // 초기화
        clk       = 1'b0;
        rst       = 1'b1;
        cpu_start = 1'b0;
        gpu_start = 1'b0;
        a_flat    = 0;
        b_flat    = 0;
        repeat (3) @(negedge clk);
        rst = 1'b0;

        // 입력 준비
        setup_vectors;

        $display("================================================================");
        $display(" CPU(Sequential) vs GPU(Parallel) Vector Multiply  C = A * B");
        $display(" N = %0d elements, DW = %0d bit, GPU lanes P = %0d", N, DW, P);
        $display(" Clock period = %0d ns (%0d MHz)", CLK_NS, 1000/CLK_NS);
        $display("================================================================");

        // 입력 벡터 출력
        $display(" Index :   A    B   ->  golden(A*B)");
        for (i = 0; i < N; i = i + 1)
            $display("   [%2d] : %3d  %3d  ->  %5d",
                     i, a_flat[i*DW +: DW], b_flat[i*DW +: DW], golden[i]);
        $display("----------------------------------------------------------------");

        // CPU 실행
        run_cpu;
        $display(" CPU  done : %0d cycles  =>  %0d ns", cpu_cycles, cpu_cycles*CLK_NS);

        // GPU 실행
        run_gpu;
        $display(" GPU  done : %0d cycles  =>  %0d ns", gpu_cycles, gpu_cycles*CLK_NS);

        // 검증
        $display("----------------------------------------------------------------");
        check_results;
        if (errors == 0)
            $display(" RESULT VERIFY : PASS  (CPU == GPU == golden, all %0d elements)", N);
        else
            $display(" RESULT VERIFY : FAIL  (%0d mismatches)", errors);

        // 시간 비교
        $display("----------------------------------------------------------------");
        $display(" TIMING COMPARISON");
        $display("   CPU  : %0d cycles (%0d ns)", cpu_cycles, cpu_cycles*CLK_NS);
        $display("   GPU  : %0d cycles (%0d ns)", gpu_cycles, gpu_cycles*CLK_NS);
        if (gpu_cycles > 0)
            $display("   Speedup (GPU vs CPU) : %0d.%02d x",
                     cpu_cycles / gpu_cycles,
                     ((cpu_cycles*100) / gpu_cycles) % 100);
        $display(" GPU uses %0d parallel PEs -> theoretical speedup ~ %0dx", P, P);
        $display("================================================================");

        if (errors == 0)
            $display(" >>> TEST PASSED <<<");
        else
            $display(" >>> TEST FAILED <<<");

        #20 $finish;
    end

    // 안전장치: 타임아웃
    initial begin
        #100000;
        $display(" [TIMEOUT] simulation did not finish in time");
        $finish;
    end

endmodule

sim/wave.vcd
$date
	Tue Jun 23 14:05:17 2026
$end
$version
	Icarus Verilog
$end
$timescale
	1ps
$end
$scope module tb_compare $end
$var wire 1 ! gpu_done $end
$var wire 256 " gpu_c [255:0] $end
$var wire 1 # gpu_busy $end
$var wire 1 $ cpu_done $end
$var wire 256 % cpu_c [255:0] $end
$var wire 1 & cpu_busy $end
$var parameter 32 ' CLK_NS $end
$var parameter 32 ( DW $end
$var parameter 32 ) N $end
$var parameter 32 * P $end
$var reg 128 + a_flat [127:0] $end
$var reg 128 , b_flat [127:0] $end
$var reg 1 - clk $end
$var reg 1 . cpu_start $end
$var reg 1 / gpu_start $end
$var reg 1 0 rst $end
$var integer 32 1 cpu_cycles [31:0] $end
$var integer 32 2 errors [31:0] $end
$var integer 32 3 gpu_cycles [31:0] $end
$var integer 32 4 i [31:0] $end
$scope module u_cpu $end
$var wire 128 5 a_flat [127:0] $end
$var wire 128 6 b_flat [127:0] $end
$var wire 1 - clk $end
$var wire 1 0 rst $end
$var wire 1 . start $end
$var wire 16 7 prod [15:0] $end
$var wire 8 8 b_elem [7:0] $end
$var wire 8 9 a_elem [7:0] $end
$var parameter 32 : DW $end
$var parameter 32 ; IDXW $end
$var parameter 32 < N $end
$var reg 1 & busy $end
$var reg 256 = c_flat [255:0] $end
$var reg 1 $ done $end
$var reg 5 > idx [4:0] $end
$upscope $end
$scope module u_gpu $end
$var wire 128 ? a_flat [127:0] $end
$var wire 128 @ b_flat [127:0] $end
$var wire 1 - clk $end
$var wire 1 0 rst $end
$var wire 1 / start $end
$var parameter 32 A DW $end
$var parameter 32 B GIDXW $end
$var parameter 32 C N $end
$var parameter 32 D NGROUP $end
$var parameter 32 E P $end
$var reg 1 # busy $end
$var reg 256 F c_flat [255:0] $end
$var reg 1 ! done $end
$var reg 3 G grp [2:0] $end
$var integer 32 H j [31:0] $end
$scope begin LANE[0] $end
$var wire 32 I gi [31:0] $end
$var wire 8 J b_in [7:0] $end
$var wire 8 K a_in [7:0] $end
$var parameter 2 L k $end
$upscope $end
$scope begin LANE[1] $end
$var wire 32 M gi [31:0] $end
$var wire 8 N b_in [7:0] $end
$var wire 8 O a_in [7:0] $end
$var parameter 2 P k $end
$upscope $end
$scope begin LANE[2] $end
$var wire 32 Q gi [31:0] $end
$var wire 8 R b_in [7:0] $end
$var wire 8 S a_in [7:0] $end
$var parameter 3 T k $end
$upscope $end
$scope begin LANE[3] $end
$var wire 32 U gi [31:0] $end
$var wire 8 V b_in [7:0] $end
$var wire 8 W a_in [7:0] $end
$var parameter 3 X k $end
$upscope $end
$upscope $end
$scope task check_results $end
$var reg 16 Y cval [15:0] $end
$var reg 16 Z gval [15:0] $end
$upscope $end
$scope task run_cpu $end
$upscope $end
$scope task run_gpu $end
$upscope $end
$scope task setup_vectors $end
$var reg 8 [ av [7:0] $end
$var reg 8 \ bv [7:0] $end
$var integer 32 ] k [31:0] $end
$upscope $end
$upscope $end
$enddefinitions $end
$comment Show the parameter values. $end
$dumpall
b11 X
b10 T
b1 P
b0 L
b100 E
b100 D
b10000 C
b10 B
b1000 A
b10000 <
b100 ;
b1000 :
b100 *
b10000 )
b1000 (
b1010 '
$end
#0
$dumpvars
bx ]
bx \
bx [
bx Z
bx Y
bx W
bx V
bx U
bx S
bx R
bx Q
bx O
bx N
bx M
bx K
bx J
bx I
bx H
bx G
bx F
b0 @
b0 ?
bx >
bx =
bx 9
bx 8
bx 7
b0 6
b0 5
bx 4
bx 3
bx 2
bx 1
10
0/
0.
0-
b0 ,
b0 +
x&
bx %
x$
x#
bx "
x!
$end
#5000
b0 K
b0 J
b0 O
b0 N
b0 S
b0 R
b0 W
b0 V
b0 %
b0 =
0$
0&
b0 7
b0 9
b0 8
b0 >
b0 "
b0 F
0!
0#
b0 I
b1 M
b10 Q
b11 U
b0 G
1-
#10000
0-
#15000
1-
#20000
0-
#25000
1-
#30000
b10010 V
b1100101 W
b10001101 R
b1101 S
b1100011 N
b1001 O
b10000001 J
b100100 K
b10000 4
b1001000100100 7
b10000001 8
b1010011001011011110111000101110011101000111101110111101010101100011010001100001111010000110100010010100011010110001110000001 ,
b1010011001011011110111000101110011101000111101110111101010101100011010001100001111010000110100010010100011010110001110000001 6
b1010011001011011110111000101110011101000111101110111101010101100011010001100001111010000110100010010100011010110001110000001 @
b100100 9
b1100011001011010101110011101000111100100001001011100101110001011111100111101101011101100000000101100101000011010000100100100100 +
b1100011001011010101110011101000111100100001001011100101110001011111100111101101011101100000000101100101000011010000100100100100 5
b1100011001011010101110011101000111100100001001011100101110001011111100111101101011101100000000101100101000011010000100100100100 ?
b1010 \
b1100011 [
b10000 ]
00
0-
#35000
1-
#40000
1.
0-
#45000
1&
1-
#50000
b0 1
0.
0-
#55000
b1001 9
b1101111011 7
b1100011 8
b1 >
b1001000100100 %
b1001000100100 =
b1 1
1-
#60000
0-
#65000
b1101 9
b11100101001 7
b10001101 8
b10 >
b11011110110001001000100100 %
b11011110110001001000100100 =
b10 1
1-
#70000
0-
#75000
b1100101 9
b11100011010 7
b10010 8
b11 >
b1110010100100000011011110110001001000100100 %
b1110010100100000011011110110001001000100100 =
b11 1
1-
#80000
0-
#85000
b1 9
b1101 7
b1101 8
b100 >
b11100011010000001110010100100000011011110110001001000100100 %
b11100011010000001110010100100000011011110110001001000100100 =
b100 1
1-
#90000
0-
#95000
b1110110 9
b1110000011110 7
b111101 8
b101 >
b11010000011100011010000001110010100100000011011110110001001000100100 %
b11010000011100011010000001110010100100000011011110110001001000100100 =
b101 1
1-
#100000
0-
#105000
b11101101 9
b1000000110011100 7
b10001100 8
b110 >
b111000001111000000000000011010000011100011010000001110010100100000011011110110001001000100100 %
b111000001111000000000000011010000011100011010000001110010100100000011011110110001001000100100 =
b110 1
1-
#110000
0-
#115000
b11111001 9
b1100000010010110 7
b11000110 8
b111 >
b1000000110011100000111000001111000000000000011010000011100011010000001110010100100000011011110110001001000100100 %
b1000000110011100000111000001111000000000000011010000011100011010000001110010100100000011011110110001001000100100 =
b111 1
1-
#120000
0-
#125000
b11000101 9
b1000001011010010 7
b10101010 8
b1000 >
b11000000100101101000000110011100000111000001111000000000000011010000011100011010000001110010100100000011011110110001001000100100 %
b11000000100101101000000110011100000111000001111000000000000011010000011100011010000001110010100100000011011110110001001000100100 =
b1000 1
1-
#130000
0-
#135000
b11100101 9
b110101001110011 7
b1110111 8
b1001 >
b100000101101001011000000100101101000000110011100000111000001111000000000000011010000011100011010000001110010100100000011011110110001001000100100 %
b100000101101001011000000100101101000000110011100000111000001111000000000000011010000011100011010000001110010100100000011011110110001001000100100 =
b1001 1
1-
#140000
0-
#145000
b10010 9
b101000001110 7
b10001111 8
b1010 >
b110101001110011100000101101001011000000100101101000000110011100000111000001111000000000000011010000011100011010000001110010100100000011011110110001001000100100 %
b110101001110011100000101101001011000000100101101000000110011100000111000001111000000000000011010000011100011010000001110010100100000011011110110001001000100100 =
b1010 1
1-
#150000
0-
#155000
b11110010 9
b1100001010111100 7
b11001110 8
b1011 >
b1010000011100110101001110011100000101101001011000000100101101000000110011100000111000001111000000000000011010000011100011010000001110010100100000011011110110001001000100100 %
b1010000011100110101001110011100000101101001011000000100101101000000110011100000111000001111000000000000011010000011100011010000001110010100100000011011110110001001000100100 =
b1011 1
1-
#160000
0-
#165000
b11101000 9
b1011001010001000 7
b11000101 8
b1100 >
b110000101011110000001010000011100110101001110011100000101101001011000000100101101000000110011100000111000001111000000000000011010000011100011010000001110010100100000011011110110001001000100100 %
b110000101011110000001010000011100110101001110011100000101101001011000000100101101000000110011100000111000001111000000000000011010000011100011010000001110010100100000011011110110001001000100100 =
b1100 1
1-
#170000
0-
#175000
b1011100 9
b100001111101100 7
b10111101 8
b1101 >
b1011001010001000110000101011110000001010000011100110101001110011100000101101001011000000100101101000000110011100000111000001111000000000000011010000011100011010000001110010100100000011011110110001001000100100 %
b1011001010001000110000101011110000001010000011100110101001110011100000101101001011000000100101101000000110011100000111000001111000000000000011010000011100011010000001110010100100000011011110110001001000100100 =
b1101 1
1-
#180000
0-
#185000
b101101 9
b1000111000001 7
b1100101 8
b1110 >
b1000011111011001011001010001000110000101011110000001010000011100110101001110011100000101101001011000000100101101000000110011100000111000001111000000000000011010000011100011010000001110010100100000011011110110001001000100100 %
b1000011111011001011001010001000110000101011110000001010000011100110101001110011100000101101001011000000100101101000000110011100000111000001111000000000000011010000011100011010000001110010100100000011011110110001001000100100 =
b1110 1
1-
#190000
0-
#195000
b1100011 9
b1111011110 7
b1010 8
b1111 >
b100011100000101000011111011001011001010001000110000101011110000001010000011100110101001110011100000101101001011000000100101101000000110011100000111000001111000000000000011010000011100011010000001110010100100000011011110110001001000100100 %
b100011100000101000011111011001011001010001000110000101011110000001010000011100110101001110011100000101101001011000000100101101000000110011100000111000001111000000000000011010000011100011010000001110010100100000011011110110001001000100100 =
b1111 1
1-
#200000
0-
#205000
b100100 9
b1001000100100 7
b10000001 8
b0 >
1$
0&
b1111011110000100011100000101000011111011001011001010001000110000101011110000001010000011100110101001110011100000101101001011000000100101101000000110011100000111000001111000000000000011010000011100011010000001110010100100000011011110110001001000100100 %
b1111011110000100011100000101000011111011001011001010001000110000101011110000001010000011100110101001110011100000101101001011000000100101101000000110011100000111000001111000000000000011010000011100011010000001110010100100000011011110110001001000100100 =
b10000 1
1-
#210000
0-
#215000
0$
b10001 1
1-
#220000
1/
0-
#225000
1#
1-
#230000
b0 3
0/
0-
#235000
b1 K
b1101 J
b1110110 O
b111101 N
b11101101 S
b10001100 R
b11111001 W
b11000110 V
b100 I
b101 M
b110 Q
b111 U
b1 G
b11100011010000001110010100100000011011110110001001000100100 "
b11100011010000001110010100100000011011110110001001000100100 F
b100 H
b1 3
1-
#240000
0-
#245000
b11000101 K
b10101010 J
b11100101 O
b1110111 N
b10010 S
b10001111 R
b11110010 W
b11001110 V
b1000 I
b1001 M
b1010 Q
b1011 U
b10 G
b11000000100101101000000110011100000111000001111000000000000011010000011100011010000001110010100100000011011110110001001000100100 "
b11000000100101101000000110011100000111000001111000000000000011010000011100011010000001110010100100000011011110110001001000100100 F
b10 3
b100 H
1-
#250000
0-
#255000
b11101000 K
b11000101 J
b1011100 O
b10111101 N
b101101 S
b1100101 R
b1100011 W
b1010 V
b1100 I
b1101 M
b1110 Q
b1111 U
b11 G
b110000101011110000001010000011100110101001110011100000101101001011000000100101101000000110011100000111000001111000000000000011010000011100011010000001110010100100000011011110110001001000100100 "
b110000101011110000001010000011100110101001110011100000101101001011000000100101101000000110011100000111000001111000000000000011010000011100011010000001110010100100000011011110110001001000100100 F
b100 H
b11 3
1-
#260000
0-
#265000
b100100 K
b10000001 J
b1001 O
b1100011 N
b1101 S
b10001101 R
b1100101 W
b10010 V
b0 I
b1 M
b10 Q
b11 U
b0 G
1!
0#
b1111011110000100011100000101000011111011001011001010001000110000101011110000001010000011100110101001110011100000101101001011000000100101101000000110011100000111000001111000000000000011010000011100011010000001110010100100000011011110110001001000100100 "
b1111011110000100011100000101000011111011001011001010001000110000101011110000001010000011100110101001110011100000101101001011000000100101101000000110011100000111000001111000000000000011010000011100011010000001110010100100000011011110110001001000100100 F
b100 3
b100 H
1-
#270000
0-
#275000
0!
b1111011110 Z
b1111011110 Y
b10000 4
b0 2
b101 3
1-
