rtl/pe/pe.sv
// -----------------------------------------------------------------------------
// pe.sv  --  Processing Element (single MAC) for the MTU systolic array
//
// Weight-stationary design (TPU / Groq style):
//   * Each PE holds one stationary weight in `w_reg`.
//   * Activations flow left -> right  (a_in  -> a_out), one PE per cycle.
//   * Partial sums flow top  -> bottom (psum_in -> psum_out), one PE per cycle.
//   * Weights are loaded by shifting them down a column: during `load_w`,
//     w_reg captures `w_in` (the weight register of the PE above) and exposes
//     it on `w_out` to the PE below.
//
// Per cycle (compute):   psum_out <= psum_in + a_in * w_reg
// This is the canonical multiply-accumulate that, when tiled into an NxN grid
// with diagonally-skewed inputs, evaluates a full matrix multiply.
// -----------------------------------------------------------------------------
`default_nettype none

module pe #(
    parameter int DATA_W = 8,    // operand width (INT8 in Phase 1/2)
    parameter int ACC_W  = 32    // accumulator width (wide enough to avoid overflow)
) (
    input  wire                       clk,
    input  wire                       rst_n,
    input  wire                       load_w,    // 1 = shift weights down the column
    input  wire signed [DATA_W-1:0]   w_in,      // weight from PE above (load chain)
    output wire signed [DATA_W-1:0]   w_out,     // weight to PE below  (load chain)
    input  wire signed [DATA_W-1:0]   a_in,      // activation from the left
    output reg  signed [DATA_W-1:0]   a_out,     // activation to the right
    input  wire signed [ACC_W-1:0]    psum_in,   // partial sum from above
    output reg  signed [ACC_W-1:0]    psum_out   // partial sum to below
);

    reg signed [DATA_W-1:0] w_reg;

    // The stationary weight is visible to the PE below for the load shift chain.
    assign w_out = w_reg;

    always_ff @(posedge clk or negedge rst_n) begin
        if (!rst_n) begin
            w_reg    <= '0;
            a_out    <= '0;
            psum_out <= '0;
        end else begin
            if (load_w) begin
                w_reg <= w_in;                       // shift weights down one row
            end
            a_out    <= a_in;                        // propagate activation right
            psum_out <= psum_in + (a_in * w_reg);    // MAC, propagate sum down
        end
    end

endmodule

`default_nettype wire

results/waves/pe.vcd
$date
	Tue Jun 23 21:40:24 2026
$end
$version
	Icarus Verilog
$end
$timescale
	1ps
$end
$scope module pe $end
$var wire 8 ! a_in [7:0] $end
$var wire 1 " clk $end
$var wire 1 # load_w $end
$var wire 32 $ psum_in [31:0] $end
$var wire 1 % rst_n $end
$var wire 8 & w_in [7:0] $end
$var wire 8 ' w_out [7:0] $end
$var parameter 32 ( ACC_W $end
$var parameter 32 ) DATA_W $end
$var reg 8 * a_out [7:0] $end
$var reg 32 + psum_out [31:0] $end
$var reg 8 , w_reg [7:0] $end
$upscope $end
$enddefinitions $end
$comment Show the parameter values. $end
$dumpall
b1000 )
b100000 (
$end
#0
$dumpvars
b0 ,
b0 +
b0 *
b0 '
b0 &
0%
b0 $
0#
1"
b0 !
$end
#5000
0"
#10000
1%
1"
#15000
0"
#20000
b111 &
1#
1"
#25000
0"
#30000
b1100100 $
b101 !
b0 &
0#
b111 '
b111 ,
1"
#35000
0"
#40000
b10000111 +
b101 *
1"
#45000
0"
#50000
1"
#50001
b0 +
b0 *
b0 '
b0 ,
0%
b0 $
b0 !
#55001
0"
#60001
1"
#65001
0"
#70001
1%
1"
#75001
0"
#80001
b11000001 &
1#
1"
#85001
0"
#90001
b11111111111111101010110111011101 $
b10010011 !
b0 &
0#
b11000001 '
b11000001 ,
1"
#95001
0"
#100001
b11111111111111101100100010110000 +
b10010011 *
1"
#105001
0"
#110001
b11000001 &
1#
1"
#115001
0"
#120001
b11111111111101101011111000111011 $
b111100 !
b0 &
0#
1"
#125001
0"
#130001
b11111111111101101010111101110111 +
b111100 *
1"
#135001
0"
#140001
b101010 &
1#
1"
#145001
0"
#150001
b11110100001101001100 $
b1010 !
b0 &
0#
b101010 '
b101010 ,
1"
#155001
0"
#160001
b11110100010011110000 +
b1010 *
1"
#165001
0"
#170001
b11010111 &
1#
1"
#175001
0"
#180001
b10101010110001001000 $
b11000101 !
b0 &
0#
b11010111 '
b11010111 ,
1"
#185001
0"
#190001
b10101011010110111011 +
b11000101 *
1"
#195001
0"
#200001
b11010010 &
1#
1"
#205001
0"
#210001
b1111101010000010000 $
b10110011 !
b0 &
0#
b11010010 '
b11010010 ,
1"
#215001
0"
#220001
b1111110000111100110 +
b10110011 *
1"
#225001
0"
#230001
b1111000 &
1#
1"
#235001
0"
#240001
b11111111111110100001101100110000 $
b101110 !
b0 &
0#
b1111000 '
b1111000 ,
1"
#245001
0"
#250001
b11111111111110100011000011000000 +
b101110 *
1"
#255001
0"
#260001
b11110010 &
1#
1"
#265001
0"
#270001
b11111111111101110000101010110100 $
b1000111 !
b0 &
0#
b11110010 '
b11110010 ,
1"
#275001
0"
#280001
b11111111111101110000011011010010 +
b1000111 *
1"
#285001
0"
#290001
b11110001 &
1#
1"
#295001
0"
#300001
b11111111111100010001000100101000 $
b10101000 !
b0 &
0#
b11110001 '
b11110001 ,
1"
#305001
0"
#310001
b11111111111100010001011001010000 +
b10101000 *
1"
#315001
0"
#320001
b10000000 &
1#
1"
#325001
0"
#330001
b1111100011111101011 $
b1111110 !
b0 &
0#
b10000000 '
b10000000 ,
1"
#335001
0"
#340001
b1111000100011101011 +
b1111110 *
1"
#345001
0"
#350001
b10001111 &
1#
1"
#355001
0"
#360001
b11101001001110110000 $
b11001000 !
b0 &
0#
b10001111 '
b10001111 ,
1"
#365001
0"
#370001
b11101010110001101000 +
b11001000 *
1"
#375001
0"
#380001
b11000 &
1#
1"
#385001
0"
#390001
b1111101011001000100 $
b110000 !
b0 &
0#
b11000 '
b11000 ,
1"
#395001
0"
#400001
b1111101101011000100 +
b110000 *
1"
#405001
0"
#410001
b11011011 &
1#
1"
#415001
0"
#420001
b100001000001010000 $
b11101000 !
b0 &
0#
b11011011 '
b11011011 ,
1"
#425001
0"
#430001
b100001001111001000 +
b11101000 *
1"
#435001
0"
#440001
b11001000 &
1#
1"
#445001
0"
#450001
b101010100001111110 $
b1101001 !
b0 &
0#
b11001000 '
b11001000 ,
1"
#455001
0"
#460001
b101001000110000110 +
b1101001 *
1"
#465001
0"
#470001
b10100010 &
1#
1"
#475001
0"
#480001
b11111111111100001111110101101101 $
b1000111 !
b0 &
0#
b10100010 '
b10100010 ,
1"
#485001
0"
#490001
b11111111111100001110001101011011 +
b1000111 *
1"
#495001
0"
#500001
b1110 &
1#
1"
#505001
0"
#510001
b10011001101011010 $
b1110110 !
b0 &
0#
b1110 '
b1110 ,
1"
#515001
0"
#520001
b10011100111001110 +
b1110110 *
1"
#525001
0"
#530001
b10111110 &
1#
1"
#535001
0"
#540001
b11111111111100110001100101100001 $
b101110 !
b0 &
0#
b10111110 '
b10111110 ,
1"
#545001
0"
#550001
b11111111111100110000110110000101 +
b101110 *
1"
#555001
0"
#560001
b1101 &
1#
1"
#565001
0"
#570001
b11111111111111010100111100010110 $
b11010011 !
b0 &
0#
b1101 '
b1101 ,
1"
#575001
0"
#580001
b11111111111111010100110011001101 +
b11010011 *
1"
#585001
0"
#590001
b10110 &
1#
1"
#595001
0"
#600001
b11111111111111110010000101100000 $
b1000110 !
b0 &
0#
b10110 '
b10110 ,
1"
#605001
0"
#610001
b11111111111111110010011101100100 +
b1000110 *
1"
#615001
0"
#620001
b11010111 &
1#
1"
#625001
0"
#630001
b111111100100100001 $
b11110110 !
b0 &
0#
b11010111 '
b11010111 ,
1"
#635001
0"
#640001
b111111101010111011 +
b11110110 *
1"
#645001
0"
#650001
b10010111 &
1#
1"
#655001
0"
#660001
b11001111001010010000 $
b1000110 !
b0 &
0#
b10010111 '
b10010111 ,
1"
#665001
0"
#670001
b11001101010111011010 +
b1000110 *
1"
#675001
0"
#680001
b1011101 &
1#
1"
#685001
0"
#690001
b11111111111101011110000011010111 $
b11111110 !
b0 &
0#
b1011101 '
b1011101 ,
1"
#695001
0"
#700001
b11111111111101011110000000011101 +
b11111110 *
1"
#705001
0"
#710001
b1010011 &
1#
1"
#715001
0"
#720001
b11111111111101101011100110100000 $
b11100100 !
b0 &
0#
b1010011 '
b1010011 ,
1"
#725001
0"
#730001
b11111111111101101011000010001100 +
b11100100 *
1"
#735001
0"
#740001
b100011 &
1#
1"
#745001
0"
#750001
b11101100001011001 $
b10111 !
b0 &
0#
b100011 '
b100011 ,
1"
#755001
0"
#760001
b11101101101111110 +
b10111 *
1"
#765001
0"
#770001
b11110000 &
1#
1"
#775001
0"
#780001
b11111111111110001111101010100100 $
b1111001 !
b0 &
0#
b11110000 '
b11110000 ,
1"
#785001
0"
#790001
b11111111111110001111001100010100 +
b1111001 *
1"
#795001
0"
#800001
b10010000 &
1#
1"
#805001
0"
#810001
b11011111111011000101 $
b1001111 !
b0 &
0#
b10010000 '
b10010000 ,
1"
#815001
0"
#820001
b11011101110000110101 +
b1001111 *
1"
#825001
0"
#830001
b10101 &
1#
1"
#835001
0"
#840001
b11111111111101000110110100111101 $
b1010010 !
b0 &
0#
b10101 '
b10101 ,
1"
#845001
0"
#850001
b11111111111101000111001111110111 +
b1010010 *
1"
#855001
0"
#860001
b10000000 &
1#
1"
#865001
0"
#870001
b11111111111111101111010010111101 $
b1101000 !
b0 &
0#
b10000000 '
b10000000 ,
1"
#875001
0"
#880001
b11111111111111101100000010111101 +
b1101000 *
1"
#885001
0"
#890001
b1100100 &
1#
1"
#895001
0"
#900001
b1001101010100110010 $
b11111100 !
b0 &
0#
b1100100 '
b1100100 ,
1"
#905001
0"
#910001
b1001101001110100010 +
b11111100 *
1"
#915001
0"
#920001
b1011101 &
1#
1"
#925001
0"
#930001
b1100010000100010110 $
b10100101 !
b0 &
0#
b1011101 '
b1011101 ,
1"
#935001
0"
#940001
b1100000000000000111 +
b10100101 *
1"
#945001
0"
#950001
b11111100 &
1#
1"
#955001
0"
#960001
b10100101110100000 $
b10111101 !
b0 &
0#
b11111100 '
b11111100 ,
1"
#965001
0"
#970001
b10100110010101100 +
b10111101 *
1"
#975001
0"
#980001
b101000 &
1#
1"
#985001
0"
#990001
b11101101010111100100 $
b10010110 !
b0 &
0#
b101000 '
b101000 ,
1"
#995001
0"
#1000001
b11101100010101010100 +
b10010110 *
1"
#1005001
0"
#1010001
b100 &
1#
1"
#1015001
0"
#1020001
b11001001101111111001 $
b1111001 !
b0 &
0#
b100 '
b100 ,
1"
#1025001
0"
#1030001
b11001001110111011101 +
b1111001 *
1"
#1035001
0"
#1040001
b11000111 &
1#
1"
#1045001
0"
#1050001
b11101001011001101110 $
b11000010 !
b0 &
0#
b11000111 '
b11000111 ,
1"
#1055001
0"
#1060001
b11101010010000111100 +
b11000010 *
1"
#1065001
0"
#1070001
b10101100 &
1#
1"
#1075001
0"
#1080001
b1010011101011101110 $
b10100010 !
b0 &
0#
b10101100 '
b10101100 ,
1"
#1085001
0"
#1090001
b1010101100111000110 +
b10100010 *
1"
#1095001
0"
#1100001
b1001010 &
1#
1"
#1105001
0"
#1110001
b11110110010111000101 $
b11100010 !
b0 &
0#
b1001010 '
b1001010 ,
1"
#1115001
0"
#1120001
b11110101110100011001 +
b11100010 *
1"
#1125001
0"
#1130001
b11111011 &
1#
1"
#1135001
0"
#1140001
b11111111111101011111101101101110 $
b1100110 !
b0 &
0#
b11111011 '
b11111011 ,
1"
#1145001
0"
#1150001
b11111111111101011111100101110000 +
b1100110 *
1"
#1155001
0"
#1160001
b10100100 &
1#
1"
#1165001
0"
#1170001
b11101110010000111000 $
b11111011 !
b0 &
0#
b10100100 '
b10100100 ,
1"
#1175001
0"
#1180001
b11101110011000000100 +
b11111011 *
1"
#1185001
0"
#1190001
b10100010 &
1#
1"
#1195001
0"
#1200001
b11111111111100110111000100111001 $
b10010100 !
b0 &
0#
b10100010 '
b10100010 ,
1"
#1205001
0"
#1210001
b11111111111100111001100011100001 +
b10010100 *
1"
#1215001
0"
#1220001
b1110 &
1#
1"
#1225001
0"
#1230001
b1110111110001101010 $
b10001 !
b0 &
0#
b1110 '
b1110 ,
1"
#1235001
0"
#1240001
b1110111110101011000 +
b10001 *
1"
#1245001
0"
#1250001
b10011010 &
1#
1"
#1255001
0"
#1260001
b11111111111111101101111011011101 $
b10111110 !
b0 &
0#
b10011010 '
b10011010 ,
1"
#1265001
0"
#1270001
b11111111111111101111100100101001 +
b10111110 *
1"
#1275001
0"
#1280001
b11110110 &
1#
1"
#1285001
0"
#1290001
b11111111111111000001010000011011 $
b101110 !
b0 &
0#
b11110110 '
b11110110 ,
1"
#1295001
0"
#1300001
b11111111111111000001001001001111 +
b101110 *
1"
#1305001
0"
#1310001
b1001 &
1#
1"
#1315001
0"
#1320001
b11100100000000011101 $
b1000101 !
b0 &
0#
b1001 '
b1001 ,
1"
#1325001
0"
#1330001
b11100100001010001010 +
b1000101 *
1"
#1335001
0"
#1340001
b11001111 &
1#
1"
#1345001
0"
#1350001
b11111111111100110010110001110000 $
b1000000 !
b0 &
0#
b11001111 '
b11001111 ,
1"
#1355001
0"
#1360001
b11111111111100110010000000110000 +
b1000000 *
1"
#1365001
0"
#1370001
b10110000 &
1#
1"
#1375001
0"
#1380001
b1010000000010111011 $
b10110110 !
b0 &
0#
b10110000 '
b10110000 ,
1"
#1385001
0"
#1390001
b1010001011111011011 +
b10110110 *
1"
#1395001
0"
#1400001
b10110100 &
1#
1"
#1405001
0"
#1410001
b1111101110001100010 $
b110100 !
b0 &
0#
b10110100 '
b10110100 ,
1"
#1415001
0"
#1420001
b1111100110011110010 +
b110100 *
1"
#1425001
0"
#1430001
b1110100 &
1#
1"
#1435001
0"
#1440001
b11111111111100100101010100100011 $
b1011101 !
b0 &
0#
b1110100 '
b1110100 ,
1"
#1445001
0"
#1450001
b11111111111100100111111101000111 +
b1011101 *
1"
#1455001
0"
#1460001
b11011111 &
1#
1"
#1465001
0"
#1470001
b10001000110111100000 $
b1100111 !
b0 &
0#
b11011111 '
b11011111 ,
1"
#1475001
0"
#1480001
b10001000000010011001 +
b1100111 *
1"
#1485001
0"
#1490001
b11111 &
1#
1"
#1495001
0"
#1500001
b11111111111111011110110011101111 $
b10000 !
b0 &
0#
b11111 '
b11111 ,
1"
#1505001
0"
#1510001
b11111111111111011110111011011111 +
b10000 *
1"
#1515001
0"
#1520001
b1000010 &
1#
1"
#1525001
0"
#1530001
b11010010101000001100 $
b101101 !
b0 &
0#
b1000010 '
b1000010 ,
1"
#1535001
0"
#1540001
b11010011010110100110 +
b101101 *
1"
#1545001
0"
#1550001
b10001000 &
1#
1"
#1555001
0"
#1560001
b11111111111110001001101000010000 $
b11011001 !
b0 &
0#
b10001000 '
b10001000 ,
1"
#1565001
0"
#1570001
b11111111111110001010110001011000 +
b11011001 *
1"
#1575001
0"
#1580001
b1010010 &
1#
1"
#1585001
0"
#1590001
b11111111111110000100011001111010 $
b11111 !
b0 &
0#
b1010010 '
b1010010 ,
1"
#1595001
0"
#1600001
b11111111111110000101000001101000 +
b11111 *
1"
#1605001
0"
#1610001
b11101001 &
1#
1"
#1615001
0"
#1620001
b100001011000100000 $
b0 &
0#
b11101001 '
b11101001 ,
1"
#1625001
0"
#1630001
b100001001101010111 +
1"
#1635001
0"
#1640001
b10100001 &
1#
1"
#1645001
0"
#1650001
b11111111111110100010101010011001 $
b111 !
b0 &
0#
b10100001 '
b10100001 ,
1"
#1655001
0"
#1660001
b11111111111110100010100000000000 +
b111 *
1"
#1665001
0"
#1670001
b11111100 &
1#
1"
#1675001
0"
#1680001
b11111111111101010111100110110111 $
b100110 !
b0 &
0#
b11111100 '
b11111100 ,
1"
#1685001
0"
#1690001
b11111111111101010111100100011111 +
b100110 *
1"
#1695001
0"
#1700001
1#
1"
#1705001
0"
#1710001
b11111111111111100110111000000101 $
b11100000 !
0#
b0 '
b0 ,
1"
#1715001
0"
#1720001
b11111111111111100110111000000101 +
b11100000 *
1"
#1725001
0"
#1730001
b110111 &
1#
1"
#1735001
0"
#1740001
b11111111111111010111101001101111 $
b11011101 !
b0 &
0#
b110111 '
b110111 ,
1"
#1745001
0"
#1750001
b11111111111111010111001011101010 +
b11011101 *
1"
#1755001
0"
#1760001
b11111001 &
1#
1"
#1765001
0"
#1770001
b11111111111110111111010011010000 $
b10011 !
b0 &
0#
b11111001 '
b11111001 ,
1"
#1775001
0"
#1780001
b11111111111110111111010001001011 +
b10011 *
1"
#1785001
0"
#1790001
b10100101 &
1#
1"
#1795001
0"
#1800001
b11111111111110100001000101001000 $
b10010000 !
b0 &
0#
b10100101 '
b10100101 ,
1"
#1805001
0"
#1810001
b11111111111110100011100100011000 +
b10010000 *
1"
#1815001
0"
#1820001
b11010100 &
1#
1"
#1825001
0"
#1830001
b11111111111101001101101100101001 $
b10 !
b0 &
0#
b11010100 '
b11010100 ,
1"
#1835001
0"
#1840001
b11111111111101001101101011010001 +
b10 *
1"
#1845001
0"
#1850001
b11111000 &
1#
1"
#1855001
0"
#1860001
b10001110111001000101 $
b111000 !
b0 &
0#
b11111000 '
b11111000 ,
1"
#1865001
0"
#1870001
b10001110110010000101 +
b111000 *
1"
#1875001
0"
#1880001
b110011 &
1#
1"
#1885001
0"
#1890001
b11110110110110001 $
b100100 !
b0 &
0#
b110011 '
b110011 ,
1"
#1895001
0"
#1900001
b11111010011011101 +
b100100 *
1"
#1905001
0"
#1910001
b101 &
1#
1"
#1915001
0"
#1920001
b11111111111111001011011110101001 $
b10111001 !
b0 &
0#
b101 '
b101 ,
1"
#1925001
0"
#1930001
b11111111111111001011011001000110 +
b10111001 *
1"
#1935001
0"
#1940001
b1001010 &
1#
1"
#1945001
0"
#1950001
b11111111111111010001101101110001 $
b11000 !
b0 &
0#
b1001010 '
b1001010 ,
1"
#1955001
0"
#1960001
b11111111111111010010001001100001 +
b11000 *
1"
#1965001
0"
#1970001
b110010 &
1#
1"
#1975001
0"
#1980001
b11000100101011110101 $
b11010110 !
b0 &
0#
b110010 '
b110010 ,
1"
#1985001
0"
#1990001
b11000100001011000001 +
b11010110 *
1"
#1995001
0"
#2000001
b110000 &
1#
1"
#2005001
0"
#2010001
b11111111111111010100000010000110 $
b11010001 !
b0 &
0#
b110000 '
b110000 ,
1"
#2015001
0"
#2020001
b11111111111111010011011110110110 +
b11010001 *
1"
#2025001
0"
#2030001
b10001000 &
1#
1"
#2035001
0"
#2040001
b1111010000101010 $
b10010100 !
b0 &
0#
b10001000 '
b10001000 ,
1"
#2045001
0"
#2050001
b10010011011001010 +
b10010100 *
1"
#2055001
0"
#2060001
b100100 &
1#
1"
#2065001
0"
#2070001
b11111111111110010001110010110011 $
b11011011 !
b0 &
0#
b100100 '
b100100 ,
1"
#2075001
0"
#2080001
b11111111111110010001011101111111 +
b11011011 *
1"
#2085001
0"
#2090001
b1000110 &
1#
1"
#2095001
0"
#2100001
b11111111111101001011001101111100 $
b1110111 !
b0 &
0#
b1000110 '
b1000110 ,
1"
#2105001
0"
#2110001
b11111111111101001101010000000110 +
b1110111 *
1"
#2115001
0"
#2120001
b11100010 &
1#
1"
#2125001
0"
#2130001
b11101000010100110110 $
b11100010 !
b0 &
0#
b11100010 '
b11100010 ,
1"
#2135001
0"
#2140001
b11101000100010111010 +
b11100010 *
1"
#2145001
0"
#2150001
b11000111 &
1#
1"
#2155001
0"
#2160001
b1011101000000 $
b11111101 !
b0 &
0#
b11000111 '
b11000111 ,
1"
#2165001
0"
#2170001
b1011111101011 +
b11111101 *
1"
#2175001
0"
#2180001
b101000 &
1#
1"
#2185001
0"
#2190001
b11111111111111111010101111111101 $
b10001 !
b0 &
0#
b101000 '
b101000 ,
1"
#2195001
0"
#2200001
b11111111111111111010111010100101 +
b10001 *
1"
#2205001
0"
#2210001
b10001110 &
1#
1"
#2215001
0"
#2220001
b11100000001110101110 $
b11011 !
b0 &
0#
b10001110 '
b10001110 ,
1"
#2225001
0"
#2230001
b11011111011110101000 +
b11011 *
1"
#2235001
0"
#2240001
b1111010 &
1#
1"
#2245001
0"
#2250001
b11111111111101010101110101111011 $
b10001110 !
b0 &
0#
b1111010 '
b1111010 ,
1"
#2255001
0"
#2260001
b11111111111101010010011100100111 +
b10001110 *
1"
#2265001
0"
#2270001
b100011 &
1#
1"
#2275001
0"
#2280001
b1000001111100100100 $
b11100101 !
b0 &
0#
b100011 '
b100011 ,
1"
#2285001
0"
#2290001
b1000001101101110011 +
b11100101 *
1"
#2295001
0"
#2300001
b1000110 &
1#
1"
#2305001
0"
#2310001
b11111111111111111100101101010000 $
b10111111 !
b0 &
0#
b1000110 '
b1000110 ,
1"
#2315001
0"
#2320001
b11111111111111111011100110001010 +
b10111111 *
1"
#2325001
0"
#2330001
b101001 &
1#
1"
#2335001
0"
#2340001
b11111111111100001001111001010000 $
b10001001 !
b0 &
0#
b101001 '
b101001 ,
1"
#2345001
0"
#2350001
b11111111111100001000101101000001 +
b10001001 *
1"
#2355001
0"
#2360001
b1111011 &
1#
1"
#2365001
0"
#2370001
b11111111111110110101111011100011 $
b11101101 !
b0 &
0#
b1111011 '
b1111011 ,
1"
#2375001
0"
#2380001
b11111111111110110101010111000010 +
b11101101 *
1"
#2385001
0"
#2390001
b10011111 &
1#
1"
#2395001
0"
#2400001
b11111111111101010111100100100110 $
b1001100 !
b0 &
0#
b10011111 '
b10011111 ,
1"
#2405001
0"
#2410001
b11111111111101010101110001011010 +
b1001100 *
1"
#2415001
0"
#2420001
b10000 &
1#
1"
#2425001
0"
#2430001
b11111111111111110000100100010101 $
b10010000 !
b0 &
0#
b10000 '
b10000 ,
1"
#2435001
0"
#2440001
b11111111111111110000001000010101 +
b10010000 *
1"
#2445001
0"
#2450001
b10110010 &
1#
1"
#2455001
0"
#2460001
b1001110101000010100 $
b11011010 !
b0 &
0#
b10110010 '
b10110010 ,
1"
#2465001
0"
#2470001
b1001111010110101000 +
b11011010 *
1"
#2475001
0"
#2480001
b100001 &
1#
1"
#2485001
0"
#2490001
b11111111111101010111111010001000 $
b10101000 !
b0 &
0#
b100001 '
b100001 ,
1"
#2495001
0"
#2500001
b11111111111101010111001100110000 +
b10101000 *
1"
#2505001
0"
#2510001
b110110 &
1#
1"
#2515001
0"
#2520001
b1001000100010000111 $
b11011011 !
b0 &
0#
b110110 '
b110110 ,
1"
#2525001
0"
#2530001
b1001000000010111001 +
b11011011 *
1"
#2535001
0"
#2540001
b1001001 &
1#
1"
#2545001
0"
#2550001
b10101000100001001010 $
b10011011 !
b0 &
0#
b1001001 '
b1001001 ,
1"
#2555001
0"
#2560001
b10100110101101111101 +
b10011011 *
1"
#2565001
0"
#2570001
b1101110 &
1#
1"
#2575001
0"
#2580001
b111011101010000001 $
b11101000 !
b0 &
0#
b1101110 '
b1101110 ,
1"
#2585001
0"
#2590001
b111011000000110001 +
b11101000 *
1"
#2595001
0"
#2600001
b1101000 &
1#
1"
#2605001
0"
#2610001
b11111111111111101100000110000100 $
b10010111 !
b0 &
0#
b1101000 '
b1101000 ,
1"
#2615001
0"
#2620001
b11111111111111101001011011011100 +
b10010111 *
1"
#2625001
0"
#2630001
b111111 &
1#
1"
#2635001
0"
#2640001
b100011011100101100 $
b1111011 !
b0 &
0#
b111111 '
b111111 ,
1"
#2645001
0"
#2650001
b100101010101110001 +
b1111011 *
1"
#2655001
0"
#2660001
b10110011 &
1#
1"
#2665001
0"
#2670001
b11111111111110101011111100011111 $
b11100100 !
b0 &
0#
b10110011 '
b10110011 ,
1"
#2675001
0"
#2680001
b11111111111110101100011110001011 +
b11100100 *
1"
#2685001
0"
#2690001
b1101011 &
1#
1"
#2695001
0"
#2700001
b11111111111101101001111110011111 $
b11101001 !
b0 &
0#
b1101011 '
b1101011 ,
1"
#2705001
0"
#2710001
b11111111111101101001011000000010 +
b11101001 *
1"
#2715001
0"
#2720001
b10111001 &
1#
1"
#2725001
0"
#2730001
b11111111111111010010000111011011 $
b11111001 !
b0 &
0#
b10111001 '
b10111001 ,
1"
#2735001
0"
#2740001
b11111111111111010010001111001100 +
b11111001 *
1"
#2745001
0"
#2750001
b10010011 &
1#
1"
#2755001
0"
#2760001
b11000111110110110001 $
b110001 !
b0 &
0#
b10010011 '
b10010011 ,
1"
#2765001
0"
#2770001
b11000110100011010100 +
b110001 *
1"
#2775001
0"
#2780001
b10100101 &
1#
1"
#2785001
0"
#2790001
b10010001001010100010 $
b1101010 !
b0 &
0#
b10100101 '
b10100101 ,
1"
#2795001
0"
#2800001
b10001110110011110100 +
b1101010 *
1"
#2805001
0"
#2810001
b10100111 &
1#
1"
#2815001
0"
#2820001
b11111111111110010100110111111000 $
b100001 !
b0 &
0#
b10100111 '
b10100111 ,
1"
#2825001
0"
#2830001
b11111111111110010100001001111111 +
b100001 *
1"
#2835001
0"
#2840001
b11000010 &
1#
1"
#2845001
0"
#2850001
b1111100011101111100 $
b10011101 !
b0 &
0#
b11000010 '
b11000010 ,
1"
#2855001
0"
#2860001
b1111101111101110110 +
b10011101 *
1"
#2865001
0"
#2870001
b11010000 &
1#
1"
#2875001
0"
#2880001
b10000001000010100101 $
b110101 !
b0 &
0#
b11010000 '
b11010000 ,
1"
#2885001
0"
#2890001
b10000000011010110101 +
b110101 *
1"
#2895001
0"
#2900001
b111000 &
1#
1"
#2905001
0"
#2910001
b11000011000100011 $
b101 !
b0 &
0#
b111000 '
b111000 ,
1"
#2915001
0"
#2920001
b11000011100111011 +
b101 *
1"
#2925001
0"
#2930001
b1111100 &
1#
1"
#2935001
0"
#2940001
b11111111111111000010101011001101 $
b1110011 !
b0 &
0#
b1111100 '
b1111100 ,
1"
#2945001
0"
#2950001
b11111111111111000110001010000001 +
b1110011 *
1"
#2955001
0"
#2960001
b11100111 &
1#
1"
#2965001
0"
#2970001
b1100000101110101110 $
b1101001 !
b0 &
0#
b11100111 '
b11100111 ,
1"
#2975001
0"
#2980001
b1100000000101101101 +
b1101001 *
1"
#2985001
0"
#2990001
b10000 &
1#
1"
#2995001
0"
#3000001
b11111111111100001110111100011100 $
b11001111 !
b0 &
0#
b10000 '
b10000 ,
1"
#3005001
0"
#3010001
b11111111111100001110110000001100 +
b11001111 *
1"
#3015001
0"
#3020001
b1010 &
1#
1"
#3025001
0"
#3030001
b11111111111111110010000111100100 $
b11011011 !
b0 &
0#
b1010 '
b1010 ,
1"
#3035001
0"
#3040001
b11111111111111110010000001110010 +
b11011011 *
1"
#3045001
0"
#3050001
b11100111 &
1#
1"
#3055001
0"
#3060001
b1110010111010001111 $
b11011000 !
b0 &
0#
b11100111 '
b11100111 ,
1"
#3065001
0"
#3070001
b1110011001001110111 +
b11011000 *
1"
#3075001
0"
#3080001
b1010101 &
1#
1"
#3085001
0"
#3090001
b11111111111111001110111111110010 $
b11011100 !
b0 &
0#
b1010101 '
b1010101 ,
1"
#3095001
0"
#3100001
b11111111111111001110001111111110 +
b11011100 *
1"
#3105001
0"
#3110001
b11011100 &
1#
1"
#3115001
0"
#3120001
b100001001010001101 $
b10111001 !
b0 &
0#
b11011100 '
b11011100 ,
1"
#3125001
0"
#3130001
b100001110010001001 +
b10111001 *
1"
#3135001
0"
#3140001
b10101100 &
1#
1"
#3145001
0"
#3150001
b11111111111111011101010110101000 $
b110 !
b0 &
0#
b10101100 '
b10101100 ,
1"
#3155001
0"
#3160001
b11111111111111011101001110110000 +
b110 *
1"
#3165001
0"
#3170001
b100100 &
1#
1"
#3175001
0"
#3180001
b10100101110111010000 $
b11000110 !
b0 &
0#
b100100 '
b100100 ,
1"
#3185001
0"
#3190001
b10100101010110101000 +
b11000110 *
1"
#3195001
0"
#3200001
b110011 &
1#
1"
#3205001
0"
#3210001
b11111111111111100111001001110000 $
b101000 !
b0 &
0#
b110011 '
b110011 ,
1"
#3215001
0"
#3220001
b11111111111111100111101001101000 +
b101000 *
1"
#3225001
0"
#3230001
b11001110 &
1#
1"
#3235001
0"
#3240001
b10111110001100010001 $
b10011000 !
b0 &
0#
b11001110 '
b11001110 ,
1"
#3245001
0"
#3250001
b10111111011101100001 +
b10011000 *
1"
#3255001
0"
#3260001
b10010000 &
1#
1"
#3265001
0"
#3270001
b11111111111101011000011010100101 $
b11001110 !
b0 &
0#
b10010000 '
b10010000 ,
1"
#3275001
0"
#3280001
b11111111111101011001110010000101 +
b11001110 *
1"
#3285001
0"
#3290001
b10001100 &
1#
1"
#3295001
0"
#3300001
b11111111111101011000000110000101 $
b0 &
0#
b10001100 '
b10001100 ,
1"
#3305001
0"
#3310001
b11111111111101011001100000101101 +
1"
#3315001
0"
#3320001
b10001001 &
1#
1"
#3325001
0"
#3330001
b11111111111101010111000100101001 $
b11010000 !
b0 &
0#
b10001001 '
b10001001 ,
1"
#3335001
0"
#3340001
b11111111111101011000011101111001 +
b11010000 *
1"
#3345001
0"
#3350001
b1100011 &
1#
1"
#3355001
0"
#3360001
b1011110100000001001 $
b11010110 !
b0 &
0#
b1100011 '
b1100011 ,
1"
#3365001
0"
#3370001
b1011101011111001011 +
b11010110 *
1"
#3375001
0"
#3380001
b110110 &
1#
1"
#3385001
0"
#3390001
b101001001111111111 $
b1011110 !
b0 &
0#
b110110 '
b110110 ,
1"
#3395001
0"
#3400001
b101010011111010011 +
b1011110 *
1"
#3405001
0"
#3410001
b11101001 &
1#
1"
#3415001
0"
#3420001
b101001000001001000 $
b100100 !
b0 &
0#
b11101001 '
b11101001 ,
1"
#3425001
0"
#3430001
b101000110100001100 +
b100100 *
1"
#3435001
0"
#3440001
b1101 &
1#
1"
#3445001
0"
#3450001
b10010011000011110101 $
b11011001 !
b0 &
0#
b1101 '
b1101 ,
1"
#3455001
0"
#3460001
b10010010111011111010 +
b11011001 *
1"
#3465001
0"
#3470001
b10101110 &
1#
1"
#3475001
0"
#3480001
b11101010111010111100 $
b10110101 !
b0 &
0#
b10101110 '
b10101110 ,
1"
#3485001
0"
#3490001
b11101100011011000010 +
b10110101 *
1"
#3495001
0"
#3500001
b10000011 &
1#
1"
#3505001
0"
#3510001
b1110010011011101111 $
b1110001 !
b0 &
0#
b10000011 '
b10000011 ,
1"
#3515001
0"
