rtl/pe/pe.sv
// -----------------------------------------------------------------------------
// pe.sv  --  Processing Element (single MAC) for the MTU systolic array
//
// Weight-stationary design (TPU / Groq style):
//   * Each PE holds one stationary weight in `w_reg`.
//   * Activations flow left -> right  (a_in  -> a_out), one PE per cycle.
//   * Partial sums flow top  -> bottom (psum_in -> psum_out), one PE per cycle.
//   * Weights are loaded by shifting them down a column: during `load_w`,
//     w_reg captures `w_in` (the weight register of the PE above) and exposes
//     it on `w_out` to the PE below.
//
// Per cycle (compute):   psum_out <= psum_in + a_in * w_reg
// This is the canonical multiply-accumulate that, when tiled into an NxN grid
// with diagonally-skewed inputs, evaluates a full matrix multiply.
// -----------------------------------------------------------------------------
`default_nettype none

module pe #(
    parameter int DATA_W = 8,    // operand width (INT8 in Phase 1/2)
    parameter int ACC_W  = 32    // accumulator width (wide enough to avoid overflow)
) (
    input  wire                       clk,
    input  wire                       rst_n,
    input  wire                       load_w,    // 1 = shift weights down the column
    input  wire signed [DATA_W-1:0]   w_in,      // weight from PE above (load chain)
    output wire signed [DATA_W-1:0]   w_out,     // weight to PE below  (load chain)
    input  wire signed [DATA_W-1:0]   a_in,      // activation from the left
    output reg  signed [DATA_W-1:0]   a_out,     // activation to the right
    input  wire signed [ACC_W-1:0]    psum_in,   // partial sum from above
    output reg  signed [ACC_W-1:0]    psum_out   // partial sum to below
);

    reg signed [DATA_W-1:0] w_reg;

    // The stationary weight is visible to the PE below for the load shift chain.
    assign w_out = w_reg;

    always_ff @(posedge clk or negedge rst_n) begin
        if (!rst_n) begin
            w_reg    <= '0;
            a_out    <= '0;
            psum_out <= '0;
        end else begin
            if (load_w) begin
                w_reg <= w_in;                       // shift weights down one row
            end
            a_out    <= a_in;                        // propagate activation right
            psum_out <= psum_in + (a_in * w_reg);    // MAC, propagate sum down
        end
    end

endmodule

`default_nettype wire

rtl/mxu/systolic_array.sv
// -----------------------------------------------------------------------------
// systolic_array.sv  --  MXU: ROWS x COLS weight-stationary systolic array
//
// Computes  Y[m][n] = sum_k  X[m][k] * W[k][n]   where
//   * W is (ROWS x COLS): PE[k][n] holds the stationary weight W[k][n].
//   * X activations enter the LEFT edge, one stream per row (contraction idx k).
//   * Y partial sums exit the BOTTOM edge, one accumulator per column n.
//
// Dataflow / timing (driven by the testbench / controller):
//   - Weights are loaded by shifting each column down: feed column n with
//     W[ROWS-1][n], W[ROWS-2][n], ... , W[0][n] over ROWS cycles with load_w=1.
//   - Activations are fed diagonally skewed: X[m][k] enters row k at cycle m+k.
//   - Output Y[m][n] emerges at the bottom of column n skewed by (m+n).
// The companion Python golden model (model/golden.py) performs the same skew so
// RTL results can be compared bit-exactly.
//
// Ports use FLATTENED packed vectors (not SV unpacked arrays) so that cocotb and
// every simulator can drive/sample them as plain integers.
// -----------------------------------------------------------------------------
`default_nettype none

module systolic_array #(
    parameter int ROWS   = 4,    // contraction dimension K (array height)
    parameter int COLS   = 4,    // output dimension      N (array width)
    parameter int DATA_W = 8,
    parameter int ACC_W  = 32
) (
    input  wire                          clk,
    input  wire                          rst_n,
    input  wire                          load_w,
    // Weight load: one DATA_W operand per column, fed into the top of each column.
    input  wire [COLS*DATA_W-1:0]        w_load_in,
    // Activations: one DATA_W operand per row, fed into the left of each row.
    input  wire [ROWS*DATA_W-1:0]        a_in,
    // Outputs: one ACC_W accumulator per column, from the bottom of each column.
    output wire [COLS*ACC_W-1:0]         y_out
);

    // Interconnect meshes between PEs.
    //   a_h[r][c]   : activation entering PE[r][c] from the left   (a_h[r][0] = a_in row r)
    //   w_v[r][c]   : weight     entering PE[r][c] from above      (w_v[0][c] = w_load_in col c)
    //   p_v[r][c]   : partial sum entering PE[r][c] from above     (p_v[0][c] = 0)
    wire signed [DATA_W-1:0] a_h [ROWS][COLS+1];
    wire signed [DATA_W-1:0] w_v [ROWS+1][COLS];
    wire signed [ACC_W-1:0]  p_v [ROWS+1][COLS];

    genvar r, c;
    generate
        // Left-edge activation inputs.
        for (r = 0; r < ROWS; r++) begin : g_a_edge
            assign a_h[r][0] = a_in[r*DATA_W +: DATA_W];
        end
        // Top-edge weight-load and zero partial-sum inputs.
        for (c = 0; c < COLS; c++) begin : g_top_edge
            assign w_v[0][c] = w_load_in[c*DATA_W +: DATA_W];
            assign p_v[0][c] = '0;
        end
        // The PE grid.
        for (r = 0; r < ROWS; r++) begin : g_row
            for (c = 0; c < COLS; c++) begin : g_col
                pe #(
                    .DATA_W (DATA_W),
                    .ACC_W  (ACC_W)
                ) u_pe (
                    .clk      (clk),
                    .rst_n    (rst_n),
                    .load_w   (load_w),
                    .w_in     (w_v[r][c]),
                    .w_out    (w_v[r+1][c]),
                    .a_in     (a_h[r][c]),
                    .a_out    (a_h[r][c+1]),
                    .psum_in  (p_v[r][c]),
                    .psum_out (p_v[r+1][c])
                );
            end
        end
        // Bottom-edge accumulator outputs.
        for (c = 0; c < COLS; c++) begin : g_y_edge
            assign y_out[c*ACC_W +: ACC_W] = p_v[ROWS][c];
        end
    endgenerate

endmodule

`default_nettype wire

results/waves/systolic_array.vcd
$date
	Tue Jun 23 21:40:25 2026
$end
$version
	Icarus Verilog
$end
$timescale
	1ps
$end
$scope module systolic_array $end
$var wire 32 ! a_in [31:0] $end
$var wire 1 " clk $end
$var wire 1 # load_w $end
$var wire 1 $ rst_n $end
$var wire 32 % w_load_in [31:0] $end
$var wire 128 & y_out [127:0] $end
$var parameter 32 ' ACC_W $end
$var parameter 32 ( COLS $end
$var parameter 32 ) DATA_W $end
$var parameter 32 * ROWS $end
$scope begin g_a_edge[0] $end
$var parameter 2 + r $end
$upscope $end
$scope begin g_a_edge[1] $end
$var parameter 2 , r $end
$upscope $end
$scope begin g_a_edge[2] $end
$var parameter 3 - r $end
$upscope $end
$scope begin g_a_edge[3] $end
$var parameter 3 . r $end
$upscope $end
$scope begin g_row[0] $end
$var parameter 2 / r $end
$scope begin g_col[0] $end
$var parameter 2 0 c $end
$scope module u_pe $end
$var wire 8 1 a_in [7:0] $end
$var wire 1 " clk $end
$var wire 1 # load_w $end
$var wire 32 2 psum_in [31:0] $end
$var wire 1 $ rst_n $end
$var wire 8 3 w_in [7:0] $end
$var wire 8 4 w_out [7:0] $end
$var parameter 32 5 ACC_W $end
$var parameter 32 6 DATA_W $end
$var reg 8 7 a_out [7:0] $end
$var reg 32 8 psum_out [31:0] $end
$var reg 8 9 w_reg [7:0] $end
$upscope $end
$upscope $end
$scope begin g_col[1] $end
$var parameter 2 : c $end
$scope module u_pe $end
$var wire 8 ; a_in [7:0] $end
$var wire 1 " clk $end
$var wire 1 # load_w $end
$var wire 32 < psum_in [31:0] $end
$var wire 1 $ rst_n $end
$var wire 8 = w_in [7:0] $end
$var wire 8 > w_out [7:0] $end
$var parameter 32 ? ACC_W $end
$var parameter 32 @ DATA_W $end
$var reg 8 A a_out [7:0] $end
$var reg 32 B psum_out [31:0] $end
$var reg 8 C w_reg [7:0] $end
$upscope $end
$upscope $end
$scope begin g_col[2] $end
$var parameter 3 D c $end
$scope module u_pe $end
$var wire 8 E a_in [7:0] $end
$var wire 1 " clk $end
$var wire 1 # load_w $end
$var wire 32 F psum_in [31:0] $end
$var wire 1 $ rst_n $end
$var wire 8 G w_in [7:0] $end
$var wire 8 H w_out [7:0] $end
$var parameter 32 I ACC_W $end
$var parameter 32 J DATA_W $end
$var reg 8 K a_out [7:0] $end
$var reg 32 L psum_out [31:0] $end
$var reg 8 M w_reg [7:0] $end
$upscope $end
$upscope $end
$scope begin g_col[3] $end
$var parameter 3 N c $end
$scope module u_pe $end
$var wire 8 O a_in [7:0] $end
$var wire 1 " clk $end
$var wire 1 # load_w $end
$var wire 32 P psum_in [31:0] $end
$var wire 1 $ rst_n $end
$var wire 8 Q w_in [7:0] $end
$var wire 8 R w_out [7:0] $end
$var parameter 32 S ACC_W $end
$var parameter 32 T DATA_W $end
$var reg 8 U a_out [7:0] $end
$var reg 32 V psum_out [31:0] $end
$var reg 8 W w_reg [7:0] $end
$upscope $end
$upscope $end
$upscope $end
$scope begin g_row[1] $end
$var parameter 2 X r $end
$scope begin g_col[0] $end
$var parameter 2 Y c $end
$scope module u_pe $end
$var wire 8 Z a_in [7:0] $end
$var wire 1 " clk $end
$var wire 1 # load_w $end
$var wire 32 [ psum_in [31:0] $end
$var wire 1 $ rst_n $end
$var wire 8 \ w_in [7:0] $end
$var wire 8 ] w_out [7:0] $end
$var parameter 32 ^ ACC_W $end
$var parameter 32 _ DATA_W $end
$var reg 8 ` a_out [7:0] $end
$var reg 32 a psum_out [31:0] $end
$var reg 8 b w_reg [7:0] $end
$upscope $end
$upscope $end
$scope begin g_col[1] $end
$var parameter 2 c c $end
$scope module u_pe $end
$var wire 8 d a_in [7:0] $end
$var wire 1 " clk $end
$var wire 1 # load_w $end
$var wire 32 e psum_in [31:0] $end
$var wire 1 $ rst_n $end
$var wire 8 f w_in [7:0] $end
$var wire 8 g w_out [7:0] $end
$var parameter 32 h ACC_W $end
$var parameter 32 i DATA_W $end
$var reg 8 j a_out [7:0] $end
$var reg 32 k psum_out [31:0] $end
$var reg 8 l w_reg [7:0] $end
$upscope $end
$upscope $end
$scope begin g_col[2] $end
$var parameter 3 m c $end
$scope module u_pe $end
$var wire 8 n a_in [7:0] $end
$var wire 1 " clk $end
$var wire 1 # load_w $end
$var wire 32 o psum_in [31:0] $end
$var wire 1 $ rst_n $end
$var wire 8 p w_in [7:0] $end
$var wire 8 q w_out [7:0] $end
$var parameter 32 r ACC_W $end
$var parameter 32 s DATA_W $end
$var reg 8 t a_out [7:0] $end
$var reg 32 u psum_out [31:0] $end
$var reg 8 v w_reg [7:0] $end
$upscope $end
$upscope $end
$scope begin g_col[3] $end
$var parameter 3 w c $end
$scope module u_pe $end
$var wire 8 x a_in [7:0] $end
$var wire 1 " clk $end
$var wire 1 # load_w $end
$var wire 32 y psum_in [31:0] $end
$var wire 1 $ rst_n $end
$var wire 8 z w_in [7:0] $end
$var wire 8 { w_out [7:0] $end
$var parameter 32 | ACC_W $end
$var parameter 32 } DATA_W $end
$var reg 8 ~ a_out [7:0] $end
$var reg 32 !" psum_out [31:0] $end
$var reg 8 "" w_reg [7:0] $end
$upscope $end
$upscope $end
$upscope $end
$scope begin g_row[2] $end
$var parameter 3 #" r $end
$scope begin g_col[0] $end
$var parameter 2 $" c $end
$scope module u_pe $end
$var wire 8 %" a_in [7:0] $end
$var wire 1 " clk $end
$var wire 1 # load_w $end
$var wire 32 &" psum_in [31:0] $end
$var wire 1 $ rst_n $end
$var wire 8 '" w_in [7:0] $end
$var wire 8 (" w_out [7:0] $end
$var parameter 32 )" ACC_W $end
$var parameter 32 *" DATA_W $end
$var reg 8 +" a_out [7:0] $end
$var reg 32 ," psum_out [31:0] $end
$var reg 8 -" w_reg [7:0] $end
$upscope $end
$upscope $end
$scope begin g_col[1] $end
$var parameter 2 ." c $end
$scope module u_pe $end
$var wire 8 /" a_in [7:0] $end
$var wire 1 " clk $end
$var wire 1 # load_w $end
$var wire 32 0" psum_in [31:0] $end
$var wire 1 $ rst_n $end
$var wire 8 1" w_in [7:0] $end
$var wire 8 2" w_out [7:0] $end
$var parameter 32 3" ACC_W $end
$var parameter 32 4" DATA_W $end
$var reg 8 5" a_out [7:0] $end
$var reg 32 6" psum_out [31:0] $end
$var reg 8 7" w_reg [7:0] $end
$upscope $end
$upscope $end
$scope begin g_col[2] $end
$var parameter 3 8" c $end
$scope module u_pe $end
$var wire 8 9" a_in [7:0] $end
$var wire 1 " clk $end
$var wire 1 # load_w $end
$var wire 32 :" psum_in [31:0] $end
$var wire 1 $ rst_n $end
$var wire 8 ;" w_in [7:0] $end
$var wire 8 <" w_out [7:0] $end
$var parameter 32 =" ACC_W $end
$var parameter 32 >" DATA_W $end
$var reg 8 ?" a_out [7:0] $end
$var reg 32 @" psum_out [31:0] $end
$var reg 8 A" w_reg [7:0] $end
$upscope $end
$upscope $end
$scope begin g_col[3] $end
$var parameter 3 B" c $end
$scope module u_pe $end
$var wire 8 C" a_in [7:0] $end
$var wire 1 " clk $end
$var wire 1 # load_w $end
$var wire 32 D" psum_in [31:0] $end
$var wire 1 $ rst_n $end
$var wire 8 E" w_in [7:0] $end
$var wire 8 F" w_out [7:0] $end
$var parameter 32 G" ACC_W $end
$var parameter 32 H" DATA_W $end
$var reg 8 I" a_out [7:0] $end
$var reg 32 J" psum_out [31:0] $end
$var reg 8 K" w_reg [7:0] $end
$upscope $end
$upscope $end
$upscope $end
$scope begin g_row[3] $end
$var parameter 3 L" r $end
$scope begin g_col[0] $end
$var parameter 2 M" c $end
$scope module u_pe $end
$var wire 8 N" a_in [7:0] $end
$var wire 1 " clk $end
$var wire 1 # load_w $end
$var wire 32 O" psum_in [31:0] $end
$var wire 1 $ rst_n $end
$var wire 8 P" w_in [7:0] $end
$var wire 8 Q" w_out [7:0] $end
$var parameter 32 R" ACC_W $end
$var parameter 32 S" DATA_W $end
$var reg 8 T" a_out [7:0] $end
$var reg 32 U" psum_out [31:0] $end
$var reg 8 V" w_reg [7:0] $end
$upscope $end
$upscope $end
$scope begin g_col[1] $end
$var parameter 2 W" c $end
$scope module u_pe $end
$var wire 8 X" a_in [7:0] $end
$var wire 1 " clk $end
$var wire 1 # load_w $end
$var wire 32 Y" psum_in [31:0] $end
$var wire 1 $ rst_n $end
$var wire 8 Z" w_in [7:0] $end
$var wire 8 [" w_out [7:0] $end
$var parameter 32 \" ACC_W $end
$var parameter 32 ]" DATA_W $end
$var reg 8 ^" a_out [7:0] $end
$var reg 32 _" psum_out [31:0] $end
$var reg 8 `" w_reg [7:0] $end
$upscope $end
$upscope $end
$scope begin g_col[2] $end
$var parameter 3 a" c $end
$scope module u_pe $end
$var wire 8 b" a_in [7:0] $end
$var wire 1 " clk $end
$var wire 1 # load_w $end
$var wire 32 c" psum_in [31:0] $end
$var wire 1 $ rst_n $end
$var wire 8 d" w_in [7:0] $end
$var wire 8 e" w_out [7:0] $end
$var parameter 32 f" ACC_W $end
$var parameter 32 g" DATA_W $end
$var reg 8 h" a_out [7:0] $end
$var reg 32 i" psum_out [31:0] $end
$var reg 8 j" w_reg [7:0] $end
$upscope $end
$upscope $end
$scope begin g_col[3] $end
$var parameter 3 k" c $end
$scope module u_pe $end
$var wire 8 l" a_in [7:0] $end
$var wire 1 " clk $end
$var wire 1 # load_w $end
$var wire 32 m" psum_in [31:0] $end
$var wire 1 $ rst_n $end
$var wire 8 n" w_in [7:0] $end
$var wire 8 o" w_out [7:0] $end
$var parameter 32 p" ACC_W $end
$var parameter 32 q" DATA_W $end
$var reg 8 r" a_out [7:0] $end
$var reg 32 s" psum_out [31:0] $end
$var reg 8 t" w_reg [7:0] $end
$upscope $end
$upscope $end
$upscope $end
$scope begin g_top_edge[0] $end
$var parameter 2 u" c $end
$upscope $end
$scope begin g_top_edge[1] $end
$var parameter 2 v" c $end
$upscope $end
$scope begin g_top_edge[2] $end
$var parameter 3 w" c $end
$upscope $end
$scope begin g_top_edge[3] $end
$var parameter 3 x" c $end
$upscope $end
$scope begin g_y_edge[0] $end
$var parameter 2 y" c $end
$upscope $end
$scope begin g_y_edge[1] $end
$var parameter 2 z" c $end
$upscope $end
$scope begin g_y_edge[2] $end
$var parameter 3 {" c $end
$upscope $end
$scope begin g_y_edge[3] $end
$var parameter 3 |" c $end
$upscope $end
$upscope $end
$enddefinitions $end
$comment Show the parameter values. $end
$dumpall
b11 |"
b10 {"
b1 z"
b0 y"
b11 x"
b10 w"
b1 v"
b0 u"
b1000 q"
b100000 p"
b11 k"
b1000 g"
b100000 f"
b10 a"
b1000 ]"
b100000 \"
b1 W"
b1000 S"
b100000 R"
b0 M"
b11 L"
b1000 H"
b100000 G"
b11 B"
b1000 >"
b100000 ="
b10 8"
b1000 4"
b100000 3"
b1 ."
b1000 *"
b100000 )"
b0 $"
b10 #"
b1000 }
b100000 |
b11 w
b1000 s
b100000 r
b10 m
b1000 i
b100000 h
b1 c
b1000 _
b100000 ^
b0 Y
b1 X
b1000 T
b100000 S
b11 N
b1000 J
b100000 I
b10 D
b1000 @
b100000 ?
b1 :
b1000 6
b100000 5
b0 0
b0 /
b11 .
b10 -
b1 ,
b0 +
b100 *
b1000 )
b100 (
b100000 '
$end
#0
$dumpvars
b0 t"
b0 s"
b0 r"
b0 o"
b0 n"
b0 m"
b0 l"
b0 j"
b0 i"
b0 h"
b0 e"
b0 d"
b0 c"
b0 b"
b0 `"
b0 _"
b0 ^"
b0 ["
b0 Z"
b0 Y"
b0 X"
b0 V"
b0 U"
b0 T"
b0 Q"
b0 P"
b0 O"
b0 N"
b0 K"
b0 J"
b0 I"
b0 F"
b0 E"
b0 D"
b0 C"
b0 A"
b0 @"
b0 ?"
b0 <"
b0 ;"
b0 :"
b0 9"
b0 7"
b0 6"
b0 5"
b0 2"
b0 1"
b0 0"
b0 /"
b0 -"
b0 ,"
b0 +"
b0 ("
b0 '"
b0 &"
b0 %"
b0 ""
b0 !"
b0 ~
b0 {
b0 z
b0 y
b0 x
b0 v
b0 u
b0 t
b0 q
b0 p
b0 o
b0 n
b0 l
b0 k
b0 j
b0 g
b0 f
b0 e
b0 d
b0 b
b0 a
b0 `
b0 ]
b0 \
b0 [
b0 Z
b0 W
b0 V
b0 U
b0 R
b0 Q
b0 P
b0 O
b0 M
b0 L
b0 K
b0 H
b0 G
b0 F
b0 E
b0 C
b0 B
b0 A
b0 >
b0 =
b0 <
b0 ;
b0 9
b0 8
b0 7
b0 4
b0 3
b0 2
b0 1
b0 &
b0 %
0$
0#
1"
b0 !
$end
#5000
0"
#10000
1$
1"
#15000
0"
#20000
b1 Q
b1000000000000000000000000 %
1#
1"
#25000
0"
#30000
b1 G
b0 Q
b10000000000000000 %
b1 R
b1 z
b1 W
1"
#35000
0"
#40000
b1 =
b0 G
b100000000 %
b1 H
b1 p
b1 M
b0 R
b0 z
b0 W
b1 {
b1 E"
b1 ""
1"
#45000
0"
#50000
b1 3
b0 =
b1 %
b1 F"
b1 n"
b1 K"
b0 {
b0 E"
b0 ""
b1 q
b1 ;"
b1 v
b0 H
b0 p
b0 M
b1 >
b1 f
b1 C
1"
#55000
0"
#60000
b1 1
b0 3
b1 !
b0 %
0#
b1 4
b1 \
b1 9
b0 >
b0 f
b0 C
b1 g
b1 1"
b1 l
b0 q
b0 ;"
b0 v
b1 <"
b1 d"
b1 A"
b0 F"
b0 n"
b0 K"
b1 o"
b1 t"
1"
#65000
0"
#70000
b101 1
b10 Z
b1000000101 !
b1 8
b1 [
b1 7
b1 ;
1"
#75000
0"
#80000
b11111111 1
b110 Z
b11 %"
b110000011011111111 !
b101 8
b101 [
b101 7
b101 ;
b1 A
b1 E
b1 a
b1 &"
b10 `
b10 d
1"
#85000
0"
#90000
b0 1
b11111110 Z
b111 %"
b100 N"
b100000001111111111000000000 !
b1 ,"
b1 O"
b11 +"
b11 /"
b10 k
b10 0"
b10 j
b10 n
b101 a
b101 &"
b110 `
b110 d
b1 K
b1 O
b101 A
b101 E
b11111111111111111111111111111111 8
b11111111111111111111111111111111 [
b11111111 7
b11111111 ;
1"
#95000
0"
#100000
b0 Z
b11111101 %"
b1000 N"
b1000111111010000000000000000 !
b0 8
b0 [
b0 7
b0 ;
b11111111 A
b11111111 E
b101 K
b101 O
b1 U
b11111111111111111111111111111111 a
b11111111111111111111111111111111 &"
b11111110 `
b11111110 d
b110 k
b110 0"
b110 j
b110 n
b10 t
b10 x
b101 ,"
b101 O"
b111 +"
b111 /"
b10 6"
b10 Y"
b11 5"
b11 9"
b1 &
b1 U"
b100 T"
b100 X"
1"
#105000
0"
#110000
b0 %"
b11111100 N"
b11111100000000000000000000000000 !
b10 _"
b100 ^"
b100 b"
b1000000000000000000000000000000101 &
b101 U"
b1000 T"
b1000 X"
b11 @"
b11 c"
b11 ?"
b11 C"
b110 6"
b110 Y"
b111 5"
b111 9"
b11111111111111111111111111111111 ,"
b11111111111111111111111111111111 O"
b11111101 +"
b11111101 /"
b10 ~
b110 t
b110 x
b11111111111111111111111111111110 k
b11111111111111111111111111111110 0"
b11111110 j
b11111110 n
b0 a
b0 &"
b0 `
b0 d
b101 U
b11111111 K
b11111111 O
b0 A
b0 E
1"
#115000
0"
#120000
b0 N"
b0 !
b0 K
b0 O
b11111111 U
b0 k
b0 0"
b0 j
b0 n
b11111110 t
b11111110 x
b110 ~
b0 ,"
b0 O"
b0 +"
b0 /"
b11111111111111111111111111111110 6"
b11111111111111111111111111111110 Y"
b11111101 5"
b11111101 9"
b111 @"
b111 c"
b111 ?"
b111 C"
b11 I"
b11111111111111111111111111111111 U"
b11111100 T"
b11111100 X"
b110 _"
b1000 ^"
b1000 b"
b110000000000000000000000000000011011111111111111111111111111111111 &
b11 i"
b100 h"
b100 l"
1"
#125000
0"
#130000
b100 s"
b100 r"
b111 i"
b1000 h"
b1000 l"
b11111111111111111111111111111110 _"
b11111100 ^"
b11111100 b"
b100000000000000000000000000000001111111111111111111111111111111111000000000000000000000000000000000 &
b0 U"
b0 T"
b0 X"
b111 I"
b11111111111111111111111111111101 @"
b11111111111111111111111111111101 c"
b11111101 ?"
b11111101 C"
b0 6"
b0 Y"
b0 5"
b0 9"
b11111110 ~
b0 t
b0 x
b0 U
1"
#135000
0"
#140000
b0 ~
b0 @"
b0 c"
b0 ?"
b0 C"
b11111101 I"
b0 _"
b0 ^"
b0 b"
b11111111111111111111111111111101 i"
b11111100 h"
b11111100 l"
b1000111111111111111111111111111111010000000000000000000000000000000000000000000000000000000000000000 &
b1000 s"
b1000 r"
1"
#145000
0"
#150000
b11111111111111111111111111111100 s"
b11111100 r"
b11111111111111111111111111111100000000000000000000000000000000000000000000000000000000000000000000000000000000000000000000000000 &
b0 i"
b0 h"
b0 l"
b0 I"
1"
#155000
0"
#160000
b0 &
b0 s"
b0 r"
1"
#165000
0"
#170000
1"
#170001
b0 4
b0 \
b0 9
b0 g
b0 1"
b0 l
b0 <"
b0 d"
b0 A"
b0 o"
b0 t"
0$
#175001
0"
#180001
1"
#185001
0"
#190001
1$
1"
#195001
0"
#200001
b101 =
b110 Q
b110000000000000010100000000 %
1#
1"
#205001
0"
#210001
b11 3
b0 =
b100 G
b0 Q
b1000000000000000011 %
b101 >
b101 f
b101 C
b110 R
b110 z
b110 W
1"
#215001
0"
#220001
b0 3
b1 =
b0 G
b10 Q
b10000000000000000100000000 %
b110 {
b110 E"
b110 ""
b101 g
b101 1"
b101 l
b0 R
b0 z
b0 W
b100 H
b100 p
b100 M
b0 >
b0 f
b0 C
b11 4
b11 \
b11 9
1"
#225001
0"
#230001
b1 3
b0 =
b10 G
b0 Q
b100000000000000001 %
b0 4
b0 \
b0 9
b1 >
b1 f
b1 C
b0 H
b0 p
b0 M
b10 R
b10 z
b10 W
b11 ]
b11 '"
b11 b
b0 g
b0 1"
b0 l
b100 q
b100 ;"
b100 v
b0 {
b0 E"
b0 ""
b101 2"
b101 Z"
b101 7"
b110 F"
b110 n"
b110 K"
1"
#235001
0"
#240001
b1 1
b0 3
b0 G
b1 !
b0 %
0#
b110 o"
b110 t"
b101 ["
b101 `"
b0 F"
b0 n"
b0 K"
b100 <"
b100 d"
b100 A"
b0 2"
b0 Z"
b0 7"
b11 ("
b11 P"
b11 -"
b10 {
b10 E"
b10 ""
b0 q
b0 ;"
b0 v
b1 g
b1 1"
b1 l
b0 ]
b0 '"
b0 b
b0 R
b0 z
b0 W
b10 H
b10 p
b10 M
b0 >
b0 f
b0 C
b1 4
b1 \
b1 9
1"
#245001
0"
#250001
b0 1
b10 Z
b1000000000 !
b1 8
b1 [
b1 7
b1 ;
1"
#255001
0"
#260001
b0 Z
b11 %"
b110000000000000000 !
b1 a
b1 &"
b10 `
b10 d
b1 A
b1 E
b0 8
b0 [
b0 7
b0 ;
1"
#265001
0"
#270001
b0 %"
b100 N"
b100000000000000000000000000 !
b0 A
b0 E
b10 L
b10 o
b1 K
b1 O
b0 a
b0 &"
b0 `
b0 d
b10 k
b10 0"
b10 j
b10 n
b1010 ,"
b1010 O"
b11 +"
b11 /"
1"
#275001
0"
#280001
b0 N"
b0 !
b1010 &
b1010 U"
b100 T"
b100 X"
b10 6"
b10 Y"
b11 5"
b11 9"
b0 ,"
b0 O"
b0 +"
b0 /"
b10 u
b10 :"
b10 t
b10 x
b0 k
b0 0"
b0 j
b0 n
b1 U
b0 L
b0 o
b0 K
b0 O
1"
#285001
0"
#290001
b0 U
b0 u
b0 :"
b0 t
b0 x
b100 !"
b100 D"
b10 ~
b0 6"
b0 Y"
b0 5"
b0 9"
b1110 @"
b1110 c"
b11 ?"
b11 C"
b0 U"
b0 T"
b0 X"
b1011000000000000000000000000000000000 &
b10110 _"
b100 ^"
b100 b"
1"
#295001
0"
#300001
b1110 i"
b100 h"
b100 l"
b11100000000000000000000000000000000000000000000000000000000000000000 &
b0 _"
b0 ^"
b0 b"
b100 J"
b100 m"
b11 I"
b0 @"
b0 c"
b0 ?"
b0 C"
b0 !"
b0 D"
b0 ~
1"
#305001
0"
#310001
b0 J"
b0 m"
b0 I"
b0 i"
b0 h"
b0 l"
b11100000000000000000000000000000000000000000000000000000000000000000000000000000000000000000000000000 &
b11100 s"
b100 r"
1"
#315001
0"
#320001
b0 &
b0 s"
b0 r"
1"
#325001
0"
#330001
1"
#330002
b0 o"
b0 t"
b0 ["
b0 `"
b0 <"
b0 d"
b0 A"
b0 ("
b0 P"
b0 -"
b0 {
b0 E"
b0 ""
b0 g
b0 1"
b0 l
b0 H
b0 p
b0 M
b0 4
b0 \
b0 9
0$
#335002
0"
#340002
1"
#345002
0"
#350002
1$
1"
#355002
0"
#360002
b1111101 3
b10110110 =
b10000000 G
b110000 Q
b110000100000001011011001111101 %
1#
1"
#365002
0"
#370002
b1101100 3
b11010001 =
b1110111 G
b1100010 Q
b1100010011101111101000101101100 %
b110000 R
b110000 z
b110000 W
b10000000 H
b10000000 p
b10000000 M
b10110110 >
b10110110 f
b10110110 C
b1111101 4
b1111101 \
b1111101 9
1"
#375002
0"
#380002
b10011111 3
b1110100 =
b1110101 G
b1101010 Q
b1101010011101010111010010011111 %
b1101100 4
b1101100 \
b1101100 9
b11010001 >
b11010001 f
b11010001 C
b1110111 H
b1110111 p
b1110111 M
b1100010 R
b1100010 z
b1100010 W
b1111101 ]
b1111101 '"
b1111101 b
b10110110 g
b10110110 1"
b10110110 l
b10000000 q
b10000000 ;"
b10000000 v
b110000 {
b110000 E"
b110000 ""
1"
#385002
0"
#390002
b1110010 3
b1000000 =
b111111 G
b11100 Q
b11100001111110100000001110010 %
b110000 F"
b110000 n"
b110000 K"
b10000000 <"
b10000000 d"
b10000000 A"
b10110110 2"
b10110110 Z"
b10110110 7"
b1111101 ("
b1111101 P"
b1111101 -"
b1100010 {
b1100010 E"
b1100010 ""
b1110111 q
b1110111 ;"
b1110111 v
b11010001 g
b11010001 1"
b11010001 l
b1101100 ]
b1101100 '"
b1101100 b
b1101010 R
b1101010 z
b1101010 W
b1110101 H
b1110101 p
b1110101 M
b1110100 >
b1110100 f
b1110100 C
b10011111 4
b10011111 \
b10011111 9
1"
#395002
0"
#400002
b11110100 1
b0 3
b0 =
b0 G
b0 Q
b11110100 !
b0 %
0#
b1110010 4
b1110010 \
b1110010 9
b1000000 >
b1000000 f
b1000000 C
b111111 H
b111111 p
b111111 M
b11100 R
b11100 z
b11100 W
b10011111 ]
b10011111 '"
b10011111 b
b1110100 g
b1110100 1"
b1110100 l
b1110101 q
b1110101 ;"
b1110101 v
b1101010 {
b1101010 E"
b1101010 ""
b1101100 ("
b1101100 P"
b1101100 -"
b11010001 2"
b11010001 Z"
b11010001 7"
b1110111 <"
b1110111 d"
b1110111 A"
b1100010 F"
b1100010 n"
b1100010 K"
b1111101 Q"
b1111101 V"
b10110110 ["
b10110110 `"
b10000000 e"
b10000000 j"
b110000 o"
b110000 t"
1"
#405002
0"
#410002
b0 1
b10011000 Z
b1001100000000000 !
b11111111111111111111101010101000 8
b11111111111111111111101010101000 [
b11110100 7
b11110100 ;
1"
#415002
0"
#420002
b0 Z
b100000 %"
b1000000000000000000000 !
b0 8
b0 [
b0 7
b0 ;
b11111111111111111111110100000000 B
b11111111111111111111110100000000 e
b11110100 A
b11110100 E
b10001000010000 a
b10001000010000 &"
b10011000 `
b10011000 d
1"
#425002
0"
#430002
b0 %"
b100 N"
b100000000000000000000000000 !
b10111110010000 ,"
b10111110010000 O"
b100000 +"
b100000 /"
b11111111111111111100110111100000 k
b11111111111111111100110111100000 0"
b10011000 j
b10011000 n
b0 a
b0 &"
b0 `
b0 d
b11111111111111111111110100001100 L
b11111111111111111111110100001100 o
b11110100 K
b11110100 O
b0 B
b0 e
b0 A
b0 E
1"
#435002
0"
#440002
b0 N"
b0 !
b0 L
b0 o
b0 K
b0 O
b11111111111111111111111010110000 V
b11111111111111111111111010110000 y
b11110100 U
b0 k
b0 0"
b0 j
b0 n
b11111111111111111100110110000100 u
b11111111111111111100110110000100 :"
b10011000 t
b10011000 x
b0 ,"
b0 O"
b0 +"
b0 /"
b11111111111111111100100000000000 6"
b11111111111111111100100000000000 Y"
b100000 5"
b100000 9"
b11000110000100 &
b11000110000100 U"
b100 T"
b100 X"
1"
#445002
0"
#450002
b11111111111111111100011011011000 _"
b100 ^"
b100 b"
b1111111111111111110001101101100000000000000000000000000000000000 &
b0 U"
b0 T"
b0 X"
b11111111111111111101110001100100 @"
b11111111111111111101110001100100 c"
b100000 ?"
b100000 C"
b0 6"
b0 Y"
b0 5"
b0 9"
b11111111111111111101001110100000 !"
b11111111111111111101001110100000 D"
b10011000 ~
b0 u
b0 :"
b0 t
b0 x
b0 V
b0 y
b0 U
1"
#455002
0"
